CHANGES.rst
LICENSE.rst
MANIFEST.in
README.rst
setup.py
src/collective/__init__.py
src/collective.dynatree.egg-info/PKG-INFO
src/collective.dynatree.egg-info/SOURCES.txt
src/collective.dynatree.egg-info/dependency_links.txt
src/collective.dynatree.egg-info/entry_points.txt
src/collective.dynatree.egg-info/namespace_packages.txt
src/collective.dynatree.egg-info/not-zip-safe
src/collective.dynatree.egg-info/requires.txt
src/collective.dynatree.egg-info/top_level.txt
src/collective/dynatree/__init__.py
src/collective/dynatree/atwidget.pt
src/collective/dynatree/atwidget.py
src/collective/dynatree/configure.zcml
src/collective/dynatree/dxwidget.pt
src/collective/dynatree/dxwidget.py
src/collective/dynatree/interfaces.py
src/collective/dynatree/tests.py
src/collective/dynatree/utils.py
src/collective/dynatree/utils.rst
src/collective/dynatree/example/__init__.py
src/collective/dynatree/example/at/__init__.py
src/collective/dynatree/example/at/archetype.py
src/collective/dynatree/example/at/configure.zcml
src/collective/dynatree/example/at/profile/archetype_tool.xml
src/collective/dynatree/example/at/profile/dexterity.py
src/collective/dynatree/example/at/profile/factorytool.xml
src/collective/dynatree/example/at/profile/metadata.xml
src/collective/dynatree/example/at/profile/types.xml
src/collective/dynatree/example/at/profile/vocabularies.xml
src/collective/dynatree/example/at/profile/types/DynatreeExample.xml
src/collective/dynatree/example/at/profile/vocabularies/ch.scb.disposition.vdex
src/collective/dynatree/example/dx/__init__.py
src/collective/dynatree/example/dx/behavior.py
src/collective/dynatree/example/dx/ch.scb.disposition.vdex
src/collective/dynatree/example/dx/configure.zcml
src/collective/dynatree/example/dx/profile/metadata.xml
src/collective/dynatree/example/dx/profile/types.xml
src/collective/dynatree/example/dx/profile/types/collective.dynatree.example.dx.xml
src/collective/dynatree/jquery.dynatree/GPL-LICENSE.txt
src/collective/dynatree/jquery.dynatree/MIT-License.txt
src/collective/dynatree/jquery.dynatree/jquery.dynatree.js
src/collective/dynatree/jquery.dynatree/jquery.dynatree.min.js
src/collective/dynatree/jquery.dynatree/version-1.2.5.txt
src/collective/dynatree/jquery.dynatree/skin/icons-rtl.gif
src/collective/dynatree/jquery.dynatree/skin/icons.gif
src/collective/dynatree/jquery.dynatree/skin/loading.gif
