Metadata-Version: 1.0
Name: collective.dynatree
Version: 2.0
Summary: jquery.dynatree.js integration for Plone
Home-page: https://github.com/collective/collective.dynatree
Author: BlueDynamics Alliance, et al.
Author-email: dev@bluedynamics.com
License: GNU General Public Licence
Keywords: jquery dynatree Zope Plone Archetypes Dexterity Widget tree vocabulary
Platform: UNKNOWN
Classifier: Environment :: Web Environment
Classifier: Framework :: Plone
Classifier: Framework :: Zope2
Classifier: License :: OSI Approved :: GNU General Public License (GPL)
Classifier: Operating System :: OS Independent
Classifier: Programming Language :: Python :: 2.6
Classifier: Programming Language :: Python :: 2.7
